posebench/__init__.py
posebench/analysis/complex_alignment.py
posebench/analysis/inference_analysis.py
posebench/analysis/inference_analysis_casp.py
posebench/analysis/similarity_scoring.py
posebench/analysis/casp15_ligand_scoring/casp_parser.py
posebench/analysis/casp15_ligand_scoring/helper.py
posebench/analysis/casp15_ligand_scoring/lddt_scoring.py
posebench/analysis/casp15_ligand_scoring/openbabel_helper.py
posebench/analysis/casp15_ligand_scoring/parse_predictions.py
posebench/analysis/casp15_ligand_scoring/score_predictions.py
posebench/data/__init__.py
posebench/data/af3_output_extraction.py
posebench/data/binding_site_crop_preparation.py
posebench/data/boltz_input_preparation.py
posebench/data/boltz_output_extraction.py
posebench/data/chai_input_preparation.py
posebench/data/chai_output_extraction.py
posebench/data/diffdock_input_preparation.py
posebench/data/dynamicbind_input_preparation.py
posebench/data/fabind_input_preparation.py
posebench/data/flowdock_input_preparation.py
posebench/data/neuralplexer_input_preparation.py
posebench/data/rfaa_input_preparation.py
posebench/data/rfaa_output_extraction.py
posebench/data/tulip_output_extraction.py
posebench/data/components/convert_mmcif_to_pdb.py
posebench/data/components/create_casp15_ensemble_input_csv.py
posebench/data/components/download_dockgen.py
posebench/data/components/esmfold_batch_structure_prediction.py
posebench/data/components/esmfold_sequence_preparation.py
posebench/data/components/fasta_preparation.py
posebench/data/components/plot_dataset_rmsd.py
posebench/data/components/prepare_boltz_msas.py
posebench/data/components/prepare_chai_msas.py
posebench/data/components/protein_apo_to_holo_alignment.py
posebench/models/__init__.py
posebench/models/boltz_inference.py
posebench/models/chai_inference.py
posebench/models/diffdock_inference.py
posebench/models/dynamicbind_inference.py
posebench/models/ensemble_generation.py
posebench/models/fabind_inference.py
posebench/models/flowdock_inference.py
posebench-1.0.0.dist-info/METADATA
posebench-1.0.0.dist-info/WHEEL
posebench-1.0.0.dist-info/licenses/LICENSE
posebench-1.0.0.dist-info/RECORD
