Metadata-Version: 2.4
Name: posebench
Version: 1.0.0
Summary: Comprehensive benchmarking of protein-ligand structure prediction methods
Project-URL: Homepage, https://pypi.org/project/posebench/
Project-URL: Repository, https://github.com/BioinfoMachineLearning/PoseBench
Author-email: Alex Morehead <acmwhb@umsystem.edu>
License: MIT License
License-File: LICENSE
Keywords: artificial intelligence,benchmarking,deep learning,molecular docking,protein-ligand docking,protein-ligand interaction,protein-ligand pose prediction,protein-ligand pose refinement,protein-ligand scoring,protein-ligand structure prediction
Classifier: Development Status :: 4 - Beta
Classifier: Intended Audience :: Developers
Classifier: License :: OSI Approved :: MIT License
Classifier: Programming Language :: Python :: 3.10
Classifier: Topic :: Scientific/Engineering :: Artificial Intelligence
Requires-Python: >=3.7
Requires-Dist: beartype
Requires-Dist: biopandas
Requires-Dist: biopython==1.79
Requires-Dist: hydra-colorlog==1.2.0
Requires-Dist: hydra-core==1.3.2
Requires-Dist: hydra-optuna-sweeper==1.2.0
Requires-Dist: ipykernel
Requires-Dist: jaxtyping>=0.2.12
Requires-Dist: joblib
Requires-Dist: lightning
Requires-Dist: loguru
Requires-Dist: lovely-numpy
Requires-Dist: lovely-tensors
Requires-Dist: meeko
Requires-Dist: numpy
Requires-Dist: omegaconf
Requires-Dist: pandas>=1.3.5
Requires-Dist: plotly
Requires-Dist: posebusters
Requires-Dist: posecheck
Requires-Dist: pre-commit
Requires-Dist: prody
Requires-Dist: prolif
Requires-Dist: pydantic>=1.10.15
Requires-Dist: pypdb
Requires-Dist: pyyaml
Requires-Dist: rdkit>=2023.3.2
Requires-Dist: rich
Requires-Dist: rootutils
Requires-Dist: scikit-learn>=1.0.2
Requires-Dist: seaborn
Requires-Dist: setuptools
Requires-Dist: spyrmsd
Requires-Dist: torch
Requires-Dist: torchmetrics
Requires-Dist: torchvision
Requires-Dist: tqdm
Requires-Dist: wrapt-timeout-decorator
Provides-Extra: examples
Provides-Extra: test
Requires-Dist: pytest; extra == 'test'
